Metadata-Version: 1.2
Name: audio2album
Version: 0.0.2
Summary: audio2album slices mp3s/youtubeURLs and tags them with metadata
Home-page: http://github.com/hoxas/Audio2Album
Author: hoxas
Author-email: hoxas@live.com
License: unlicense
Download-URL: https://github.com/hoxas/Audio2Album/archive/refs/tags/v0.0.2.tar.gz
Keywords: audio,album,music,cli,albums,cut,slice,id3
Platform: UNKNOWN
Classifier: Intended Audience :: End Users/Desktop
Classifier: Topic :: Multimedia :: Sound/Audio
Classifier: License :: Public Domain
Classifier: Programming Language :: Python :: 3
Classifier: Programming Language :: Python :: 3.6
Classifier: Programming Language :: Python :: 3.9
Requires-Python: >=3.6
